MANIFEST.in
requirements.txt
setup.py
ParallelPyFrontend/FrontendClientRunner.py
ParallelPyFrontend/OptConstraint.py
ParallelPyFrontend/OptMPModel.py
ParallelPyFrontend/OptObject.py
ParallelPyFrontend/OptVariable.py
ParallelPyFrontend/OptimizerMPModel.py
ParallelPyFrontend/OptimizerRoutingModel.py
ParallelPyFrontend/Parallel.py
ParallelPyFrontend/ParallelMPToolbox.py
ParallelPyFrontend/ParallelModel.py
ParallelPyFrontend/ParallelRoutingToolbox.py
ParallelPyFrontend/VRPRoutingModel.py
ParallelPyFrontend/__init__.py
ParallelPyFrontend/cp_routing_model_pb2.py
ParallelPyFrontend/linear_model_pb2.py
ParallelPyFrontend/meta_bb_packet_pb2.py
ParallelPyFrontend/meta_bb_paramset_pb2.py
ParallelPyFrontend/network_packet_pb2.py
ParallelPyFrontend/optilab_pb2.py
ParallelPyFrontend/optimizer_model_pb2.py
ParallelPyFrontend/parallelbb_parameter_set_pb2.py
ParallelPyFrontend/routing_model_pb2.py
ParallelPyFrontend.egg-info/PKG-INFO
ParallelPyFrontend.egg-info/SOURCES.txt
ParallelPyFrontend.egg-info/dependency_links.txt
ParallelPyFrontend.egg-info/requires.txt
ParallelPyFrontend.egg-info/top_level.txt