Metadata-Version: 1.0
Name: ParallelPyFrontend
Version: 0.1.2
Summary: Parallel AI Frontend Python SDK
Home-page: UNKNOWN
Author: Austin Garrett
Author-email: agarrett777@gmail.com
License: UNKNOWN
Platform: UNKNOWN
